{"type":"FeatureCollection","features":[{"type":"Feature","properties":{"id":20901,"name":"А.С. \"НОВЫЙ ПЕТЕРГОФ\" (ПОСАДКИ И ВЫСАДКИ НЕТ)","transportType":{"name":"Автобус","systemName":"bus","monitorable":true,"id":0}},"id":20901,"geometry":{"type":"Point","coordinates":[3331611.7992286105,8369676.687174775]}},{"type":"Feature","properties":{"id":22317,"name":"ПЕТРОДВОРЕЦ, ВОКЗАЛ","transportType":{"name":"Автобус","systemName":"bus","monitorable":true,"id":0}},"id":22317,"geometry":{"type":"Point","coordinates":[3331294.6499993415,8369674.691580731]}},{"type":"Feature","properties":{"id":2490,"name":"ЭРЛЕРОВСКИЙ БУЛЬВАР,УГ. УЛ. АВРОВА","transportType":{"name":"Автобус","systemName":"bus","monitorable":true,"id":0}},"id":2490,"geometry":{"type":"Point","coordinates":[3330397.6375425295,8371014.300127421]}},{"type":"Feature","properties":{"id":14744,"name":"КОНСТАНТИНОВСКАЯ УЛ.","transportType":{"name":"Автобус","systemName":"bus","monitorable":true,"id":0}},"id":14744,"geometry":{"type":"Point","coordinates":[3330015.811689108,8371391.9890861735]}},{"type":"Feature","properties":{"id":2222,"name":"УЛ. ЖАРНОВЕЦКОГО","transportType":{"name":"Автобус","systemName":"bus","monitorable":true,"id":0}},"id":2222,"geometry":{"type":"Point","coordinates":[3329280.8804108906,8371535.928489433]}},{"type":"Feature","properties":{"id":19952,"name":"УНИВЕРСАМ","transportType":{"name":"Автобус","systemName":"bus","monitorable":true,"id":0}},"id":19952,"geometry":{"type":"Point","coordinates":[3328494.853486399,8371909.429967734]}},{"type":"Feature","properties":{"id":19928,"name":"БУЛЬВ. РАЗВЕДЧИКОВ, УГ. РАЗВОДНОЙ УЛ.","transportType":{"name":"Автобус","systemName":"bus","monitorable":true,"id":0}},"id":19928,"geometry":{"type":"Point","coordinates":[3328585.801510378,8372532.49205118]}},{"type":"Feature","properties":{"id":19885,"name":"МАСТЕРОВОЙ ПЕР. УГ. Б-РА РАЗВЕДЧИКА","transportType":{"name":"Автобус","systemName":"bus","monitorable":true,"id":0}},"id":19885,"geometry":{"type":"Point","coordinates":[3327754.801511606,8372758.972304988]}},{"type":"Feature","properties":{"id":1678,"name":"МАСТЕРОВОЙ ПЕР.","transportType":{"name":"Автобус","systemName":"bus","monitorable":true,"id":0}},"id":1678,"geometry":{"type":"Point","coordinates":[3327857.9946795707,8373571.11981218]}},{"type":"Feature","properties":{"id":2436,"name":"ФАБРИЧНАЯ УЛ.","transportType":{"name":"Автобус","systemName":"bus","monitorable":true,"id":0}},"id":2436,"geometry":{"type":"Point","coordinates":[3327239.837547196,8373769.45622926]}},{"type":"Feature","properties":{"id":14690,"name":"ЖЕЛЕЗНОДОРОЖНЫЙ ПЕРЕЕЗД","transportType":{"name":"Автобус","systemName":"bus","monitorable":true,"id":0}},"id":14690,"geometry":{"type":"Point","coordinates":[3325082.3544961317,8372692.424985718]}},{"type":"Feature","properties":{"id":1525,"name":"Ж.Д. СТ. СТАРЫЙ ПЕТЕРГОФ","transportType":{"name":"Автобус","systemName":"bus","monitorable":true,"id":0}},"id":1525,"geometry":{"type":"Point","coordinates":[3324269.6108938497,8372883.195574504]}},{"type":"Feature","properties":{"id":19963,"name":"УЛ. ДЗЕРЖИНСКОГО","transportType":{"name":"Автобус","systemName":"bus","monitorable":true,"id":0}},"id":19963,"geometry":{"type":"Point","coordinates":[3322615.180621681,8373077.298622768]}},{"type":"Feature","properties":{"id":19967,"name":"ЛЕСНАЯ УЛ.","transportType":{"name":"Автобус","systemName":"bus","monitorable":true,"id":0}},"id":19967,"geometry":{"type":"Point","coordinates":[3322101.9977691234,8373314.6658663675]}},{"type":"Feature","properties":{"id":19969,"name":"УЛ. ПЕРВОГО МАЯ,89","transportType":{"name":"Автобус","systemName":"bus","monitorable":true,"id":0}},"id":19969,"geometry":{"type":"Point","coordinates":[3321236.6000476964,8373704.009058922]}},{"type":"Feature","properties":{"id":3853,"name":"Г.ПЕТЕРГОФ, УНИВЕРСИТЕТ","transportType":{"name":"Автобус","systemName":"bus","monitorable":true,"id":0}},"id":3853,"geometry":{"type":"Point","coordinates":[3320301.961602996,8373382.328022208]}},{"type":"Feature","properties":{"id":3850,"name":"ГОР. ПЕТРОДВОРЕЦ, УНИВЕРСИТЕТ","transportType":{"name":"Автобус","systemName":"bus","monitorable":true,"id":0}},"id":3850,"geometry":{"type":"Point","coordinates":[3320320.2179994867,8373377.669296492]}},{"type":"Feature","properties":{"id":19970,"name":"УЛ. ПЕРВОГО МАЯ,89","transportType":{"name":"Автобус","systemName":"bus","monitorable":true,"id":0}},"id":19970,"geometry":{"type":"Point","coordinates":[3321338.1234232998,8373610.83103901]}},{"type":"Feature","properties":{"id":19968,"name":"ЛЕСНАЯ УЛ.","transportType":{"name":"Автобус","systemName":"bus","monitorable":true,"id":0}},"id":19968,"geometry":{"type":"Point","coordinates":[3322140.7369519197,8373256.099780306]}},{"type":"Feature","properties":{"id":19964,"name":"УЛ. ДЗЕРЖИНСКОГО","transportType":{"name":"Автобус","systemName":"bus","monitorable":true,"id":0}},"id":19964,"geometry":{"type":"Point","coordinates":[3322672.2875204575,8373017.181589641]}},{"type":"Feature","properties":{"id":26118,"name":"УЛ. ПЕРВОГО МАЯ УГ. ГОСТИЛИЦКОЙ УЛ.","transportType":{"name":"Автобус","systemName":"bus","monitorable":true,"id":0}},"id":26118,"geometry":{"type":"Point","coordinates":[3324029.272113227,8372469.717658669]}},{"type":"Feature","properties":{"id":2733,"name":"Ж.Д. СТ. СТАРЫЙ ПЕТЕРГОФ","transportType":{"name":"Автобус","systemName":"bus","monitorable":true,"id":0}},"id":2733,"geometry":{"type":"Point","coordinates":[3324486.015983952,8372749.655644134]}},{"type":"Feature","properties":{"id":14689,"name":"ЖЕЛЕЗНОДОРОЖНЫЙ ПЕРЕЕЗД","transportType":{"name":"Автобус","systemName":"bus","monitorable":true,"id":0}},"id":14689,"geometry":{"type":"Point","coordinates":[3324950.997496995,8372496.557527881]}},{"type":"Feature","properties":{"id":3616,"name":"ФАБРИЧНАЯ УЛ.","transportType":{"name":"Автобус","systemName":"bus","monitorable":true,"id":0}},"id":3616,"geometry":{"type":"Point","coordinates":[3327360.3965557255,8373660.303983918]}},{"type":"Feature","properties":{"id":19978,"name":"С.-ПЕТЕРБУРГСКИЙ ПР., УГ. МАСТЕРОВОГО ПЕР.","transportType":{"name":"Автобус","systemName":"bus","monitorable":true,"id":0}},"id":19978,"geometry":{"type":"Point","coordinates":[3327897.735737784,8373464.854508471]}},{"type":"Feature","properties":{"id":19929,"name":"МАСТЕРОВОЙ ПЕР., УГ. БУЛЬВ. РАЗВЕДЧИКА","transportType":{"name":"Автобус","systemName":"bus","monitorable":true,"id":0}},"id":19929,"geometry":{"type":"Point","coordinates":[3327708.047325473,8372801.119251151]}},{"type":"Feature","properties":{"id":25679,"name":"БУЛЬВАР РАЗВЕДЧИКОВ, 10","transportType":{"name":"Автобус","systemName":"bus","monitorable":true,"id":0}},"id":25679,"geometry":{"type":"Point","coordinates":[3327962.7463204074,8372579.739561264]}},{"type":"Feature","properties":{"id":19980,"name":"БУЛЬВАР РАЗВЕДЧИКОВ, УГ. РАЗВОДНОЙ УЛ.","transportType":{"name":"Автобус","systemName":"bus","monitorable":true,"id":0}},"id":19980,"geometry":{"type":"Point","coordinates":[3328579.678938384,8372357.922890732]}},{"type":"Feature","properties":{"id":19981,"name":"УНИВЕРСАМ","transportType":{"name":"Автобус","systemName":"bus","monitorable":true,"id":0}},"id":19981,"geometry":{"type":"Point","coordinates":[3328451.3275654996,8371918.301966827]}},{"type":"Feature","properties":{"id":19931,"name":"ЭРЛЕРОВСКИЙ БУЛЬВАР","transportType":{"name":"Автобус","systemName":"bus","monitorable":true,"id":0}},"id":19931,"geometry":{"type":"Point","coordinates":[3328489.176192369,8371672.551538937]}},{"type":"Feature","properties":{"id":3405,"name":"УЛ. ЖАРНОВЕЦКОГО","transportType":{"name":"Автобус","systemName":"bus","monitorable":true,"id":0}},"id":3405,"geometry":{"type":"Point","coordinates":[3329345.7796740225,8371509.757479868]}},{"type":"Feature","properties":{"id":19937,"name":"КОНСТАНТИНОВСКАЯ УЛ.","transportType":{"name":"Автобус","systemName":"bus","monitorable":true,"id":0}},"id":19937,"geometry":{"type":"Point","coordinates":[3330090.061789467,8371248.052492414]}},{"type":"Feature","properties":{"id":3668,"name":"ЭРЛЕРОВСКИЙ БУЛЬВАР,УГ. УЛ. АВРОВА","transportType":{"name":"Автобус","systemName":"bus","monitorable":true,"id":0}},"id":3668,"geometry":{"type":"Point","coordinates":[3330463.0934031154,8370915.611837247]}},{"type":"Feature","properties":{"id":20902,"name":"ПЕТРОДВОРЕЦ, ВОКЗАЛ","transportType":{"name":"Автобус","systemName":"bus","monitorable":true,"id":0}},"id":20902,"geometry":{"type":"Point","coordinates":[3331267.8220020602,8369633.671156188]}}]}