{"type":"FeatureCollection","features":[{"type":"Feature","properties":{"id":22165,"name":"А.С. \"НАЛИЧНАЯ УЛ.\"","transportType":{"name":"Автобус","systemName":"bus","monitorable":true,"id":0}},"id":22165,"geometry":{"type":"Point","coordinates":[3365975.0128415874,8390122.157413263]}},{"type":"Feature","properties":{"id":2246,"name":"УЛ. КОРАБЛЕСТРОИТЕЛЕЙ","transportType":{"name":"Автобус","systemName":"bus","monitorable":true,"id":0}},"id":2246,"geometry":{"type":"Point","coordinates":[3365767.2906717667,8389661.910287615]}},{"type":"Feature","properties":{"id":2424,"name":"УНИВЕРСАМ \"ГАВАНСКИЙ\"","transportType":{"name":"Автобус","systemName":"bus","monitorable":true,"id":0}},"id":2424,"geometry":{"type":"Point","coordinates":[3365516.042581046,8388776.84915386]}},{"type":"Feature","properties":{"id":3284,"name":"СТ. МЕТРО \"ПРИМОРСКАЯ\"","transportType":{"name":"Автобус","systemName":"bus","monitorable":true,"id":0}},"id":3284,"geometry":{"type":"Point","coordinates":[3365269.135950467,8388305.126766648]}},{"type":"Feature","properties":{"id":2870,"name":"МАГАЗИН \"СТРОИТЕЛЬ\"","transportType":{"name":"Автобус","systemName":"bus","monitorable":true,"id":0}},"id":2870,"geometry":{"type":"Point","coordinates":[3364523.963279097,8388512.974332537]}},{"type":"Feature","properties":{"id":1732,"name":"НОВОСМОЛЕНСКАЯ НАБ.,УГ. УЛ. КОРАБЛЕСТРОИТЕЛЕЙ","transportType":{"name":"Автобус","systemName":"bus","monitorable":true,"id":0}},"id":1732,"geometry":{"type":"Point","coordinates":[3363592.9983775923,8388382.929981763]}},{"type":"Feature","properties":{"id":24689,"name":"Мичманская ул.","transportType":{"name":"Автобус","systemName":"bus","monitorable":true,"id":0}},"id":24689,"geometry":{"type":"Point","coordinates":[3363376.8159264717,8387537.808774204]}},{"type":"Feature","properties":{"id":2247,"name":"БОЦМАНСКАЯ УЛ.","transportType":{"name":"Автобус","systemName":"bus","monitorable":true,"id":0}},"id":2247,"geometry":{"type":"Point","coordinates":[3363493.590072314,8387049.496488818]}},{"type":"Feature","properties":{"id":1458,"name":"ГОСТИНИЦА \"ПРИБАЛТИЙСКАЯ\"","transportType":{"name":"Автобус","systemName":"bus","monitorable":true,"id":0}},"id":1458,"geometry":{"type":"Point","coordinates":[3364033.489602661,8386333.86739473]}},{"type":"Feature","properties":{"id":2279,"name":"УЛ. НАХИМОВА,18","transportType":{"name":"Автобус","systemName":"bus","monitorable":true,"id":0}},"id":2279,"geometry":{"type":"Point","coordinates":[3364760.1832385603,8386708.7861443525]}},{"type":"Feature","properties":{"id":2278,"name":"УЛ. НАХИМОВА","transportType":{"name":"Автобус","systemName":"bus","monitorable":true,"id":0}},"id":2278,"geometry":{"type":"Point","coordinates":[3365326.1315297526,8386874.583209278]}},{"type":"Feature","properties":{"id":1672,"name":"МАЛЫЙ ПР. В.О.,УГ. НАЛИЧНОЙ УЛ.","transportType":{"name":"Автобус","systemName":"bus","monitorable":true,"id":0}},"id":1672,"geometry":{"type":"Point","coordinates":[3365858.3500152356,8385843.63490248]}},{"type":"Feature","properties":{"id":19770,"name":"УЛ. БЕРИНГА","transportType":{"name":"Автобус","systemName":"bus","monitorable":true,"id":0}},"id":19770,"geometry":{"type":"Point","coordinates":[3366785.975332016,8386030.523860219]}},{"type":"Feature","properties":{"id":24536,"name":"24-25-Я ЛИНИИ В.О.","transportType":{"name":"Автобус","systemName":"bus","monitorable":true,"id":0}},"id":24536,"geometry":{"type":"Point","coordinates":[3367515.006677221,8386430.984410422]}},{"type":"Feature","properties":{"id":19780,"name":"16-17-Я ЛИНИИ В.О.","transportType":{"name":"Автобус","systemName":"bus","monitorable":true,"id":0}},"id":19780,"geometry":{"type":"Point","coordinates":[3368632.431725804,8387064.83215856]}},{"type":"Feature","properties":{"id":19806,"name":"12-13 ЛИНИИ В.О.","transportType":{"name":"Автобус","systemName":"bus","monitorable":true,"id":0}},"id":19806,"geometry":{"type":"Point","coordinates":[3369311.9258976057,8387466.237994902]}},{"type":"Feature","properties":{"id":19810,"name":"8-9-Я ЛИНИИ В.О., УГ. МАЛОГО ПР. В.О.","transportType":{"name":"Автобус","systemName":"bus","monitorable":true,"id":0}},"id":19810,"geometry":{"type":"Point","coordinates":[3369898.356975104,8387811.428938545]}},{"type":"Feature","properties":{"id":26145,"name":"НАБ. МАКАРОВА","transportType":{"name":"Автобус","systemName":"bus","monitorable":true,"id":0}},"id":26145,"geometry":{"type":"Point","coordinates":[3370861.047931485,8388292.67832846]}},{"type":"Feature","properties":{"id":26151,"name":"1-Я И КАДЕТСКАЯ ЛИНИИ В.О.","transportType":{"name":"Автобус","systemName":"bus","monitorable":true,"id":0}},"id":26151,"geometry":{"type":"Point","coordinates":[3371204.245921601,8387889.671503439]}},{"type":"Feature","properties":{"id":2776,"name":"КАДЕТСКАЯ ЛИНИЯ УГ. СРЕДНЕГО ПР.","transportType":{"name":"Автобус","systemName":"bus","monitorable":true,"id":0}},"id":2776,"geometry":{"type":"Point","coordinates":[3371324.248332676,8387528.695686049]}},{"type":"Feature","properties":{"id":2059,"name":"СТ. МЕТРО \"ВАСИЛЕОСТРОВСКАЯ\"","transportType":{"name":"Автобус","systemName":"bus","monitorable":true,"id":0}},"id":2059,"geometry":{"type":"Point","coordinates":[3370809.0617292845,8387227.525576671]}},{"type":"Feature","properties":{"id":4983,"name":"СРЕДНИЙ ПР. В.О. ПО 9 ЛИНИИ","transportType":{"name":"Автобус","systemName":"bus","monitorable":true,"id":0}},"id":4983,"geometry":{"type":"Point","coordinates":[3370214.8382874303,8387166.403994252]}},{"type":"Feature","properties":{"id":19818,"name":"8-9-Я ЛИНИИ В.О., УГ. МАЛОГО ПР. В.О.","transportType":{"name":"Автобус","systemName":"bus","monitorable":true,"id":0}},"id":19818,"geometry":{"type":"Point","coordinates":[3369726.3683618293,8387778.976300265]}},{"type":"Feature","properties":{"id":19807,"name":"12-13 ЛИНИИ В.О.","transportType":{"name":"Автобус","systemName":"bus","monitorable":true,"id":0}},"id":19807,"geometry":{"type":"Point","coordinates":[3369196.153627181,8387443.566650781]}},{"type":"Feature","properties":{"id":19781,"name":"16-17-Я ЛИНИИ В.О.","transportType":{"name":"Автобус","systemName":"bus","monitorable":true,"id":0}},"id":19781,"geometry":{"type":"Point","coordinates":[3368603.7112971786,8387105.505176347]}},{"type":"Feature","properties":{"id":19777,"name":"24-25-Я ЛИНИИ В.О.","transportType":{"name":"Автобус","systemName":"bus","monitorable":true,"id":0}},"id":19777,"geometry":{"type":"Point","coordinates":[3367402.2400330477,8386422.317164788]}},{"type":"Feature","properties":{"id":19772,"name":"УЛ. БЕРИНГА","transportType":{"name":"Автобус","systemName":"bus","monitorable":true,"id":0}},"id":19772,"geometry":{"type":"Point","coordinates":[3366754.9171940843,8386085.413669745]}},{"type":"Feature","properties":{"id":2662,"name":"ГАВАНСКАЯ УЛ. УГ. МАЛОГО ПР.","transportType":{"name":"Автобус","systemName":"bus","monitorable":true,"id":0}},"id":2662,"geometry":{"type":"Point","coordinates":[3365931.93219865,8385896.745551097]}},{"type":"Feature","properties":{"id":2875,"name":"МАЛЫЙ ПР. В.О.,УГ. НАЛИЧНОЙ УЛ.","transportType":{"name":"Автобус","systemName":"bus","monitorable":true,"id":0}},"id":2875,"geometry":{"type":"Point","coordinates":[3365566.358990885,8386064.746608451]}},{"type":"Feature","properties":{"id":2908,"name":"НАЛИЧНАЯ УЛ. УГ. УЛ. НАХИМОВА","transportType":{"name":"Автобус","systemName":"bus","monitorable":true,"id":0}},"id":2908,"geometry":{"type":"Point","coordinates":[3365175.961536673,8386965.039749085]}},{"type":"Feature","properties":{"id":24676,"name":"УЛ. НАХИМОВА, 11","transportType":{"name":"Автобус","systemName":"bus","monitorable":true,"id":0}},"id":24676,"geometry":{"type":"Point","coordinates":[3364461.8470032336,8386624.333309332]}},{"type":"Feature","properties":{"id":2671,"name":"ГОСТИНИЦА \"ПРИБАЛТИЙСКАЯ\"","transportType":{"name":"Автобус","systemName":"bus","monitorable":true,"id":0}},"id":2671,"geometry":{"type":"Point","coordinates":[3363864.2839766555,8386410.094143399]}},{"type":"Feature","properties":{"id":3429,"name":"БОЦМАНСКАЯ УЛ.","transportType":{"name":"Автобус","systemName":"bus","monitorable":true,"id":0}},"id":3429,"geometry":{"type":"Point","coordinates":[3363551.6988465083,8387138.843882931]}},{"type":"Feature","properties":{"id":2883,"name":"МИЧМАНСКАЯ УЛ.","transportType":{"name":"Автобус","systemName":"bus","monitorable":true,"id":0}},"id":2883,"geometry":{"type":"Point","coordinates":[3363513.182302694,8387840.3252436]}},{"type":"Feature","properties":{"id":2926,"name":"НОВОСМОЛЕНСКАЯ НАБ.,УГ. УЛ. КОРАБЛЕСТРОИТЕЛЕЙ","transportType":{"name":"Автобус","systemName":"bus","monitorable":true,"id":0}},"id":2926,"geometry":{"type":"Point","coordinates":[3363866.733005453,8388378.484061624]}},{"type":"Feature","properties":{"id":2925,"name":"НОВОСМОЛЕНСКАЯ НАБ.,6","transportType":{"name":"Автобус","systemName":"bus","monitorable":true,"id":0}},"id":2925,"geometry":{"type":"Point","coordinates":[3364605.0038683945,8388163.527023229]}},{"type":"Feature","properties":{"id":3285,"name":"СТ. МЕТРО \"ПРИМОРСКАЯ\"","transportType":{"name":"Автобус","systemName":"bus","monitorable":true,"id":0}},"id":3285,"geometry":{"type":"Point","coordinates":[3365452.5904712947,8388352.030892277]}},{"type":"Feature","properties":{"id":3605,"name":"УНИВЕРСАМ \"ГАВАНСКИЙ\"","transportType":{"name":"Автобус","systemName":"bus","monitorable":true,"id":0}},"id":3605,"geometry":{"type":"Point","coordinates":[3365603.0944228456,8388890.44939611]}},{"type":"Feature","properties":{"id":24640,"name":"НАЛИЧНАЯ УЛ., УГ. УРАЛЬСКОЙ УЛ. ","transportType":{"name":"Автобус","systemName":"bus","monitorable":true,"id":0}},"id":24640,"geometry":{"type":"Point","coordinates":[3365890.4100285843,8389874.687631896]}}]}