{"type":"FeatureCollection","features":[{"type":"Feature","properties":{"id":16883,"name":"Ж/Д ПЛАТФОРМА СОРТИРОВОЧНАЯ (посадки нет)","transportType":{"name":"Троллейбус","systemName":"trolley","monitorable":true,"id":1}},"id":16883,"geometry":{"type":"Point","coordinates":[3386660.511940284,8369970.710597626]}},{"type":"Feature","properties":{"id":15316,"name":"Ж/Д ПЛАТФОРМА СОРТИРОВОЧНАЯ (посадка)","transportType":{"name":"Троллейбус","systemName":"trolley","monitorable":true,"id":1}},"id":15316,"geometry":{"type":"Point","coordinates":[3386795.3198436345,8370164.071756691]}},{"type":"Feature","properties":{"id":25033,"name":"СОФИЙСКАЯ УЛИЦА","transportType":{"name":"Троллейбус","systemName":"trolley","monitorable":true,"id":1}},"id":25033,"geometry":{"type":"Point","coordinates":[3385726.652732019,8370097.547850087]}},{"type":"Feature","properties":{"id":25032,"name":"СОФИЙСКАЯ УЛИЦА, 40","transportType":{"name":"Троллейбус","systemName":"trolley","monitorable":true,"id":1}},"id":25032,"geometry":{"type":"Point","coordinates":[3385203.4511252907,8370807.167126772]}},{"type":"Feature","properties":{"id":25031,"name":"СОФИЙСКАЯ УЛИЦА, 32","transportType":{"name":"Троллейбус","systemName":"trolley","monitorable":true,"id":1}},"id":25031,"geometry":{"type":"Point","coordinates":[3384619.023798626,8371583.391404767]}},{"type":"Feature","properties":{"id":25030,"name":"УЛИЦА БЕЛЫ КУНА","transportType":{"name":"Троллейбус","systemName":"trolley","monitorable":true,"id":1}},"id":25030,"geometry":{"type":"Point","coordinates":[3383667.2421523435,8372514.968403737]}},{"type":"Feature","properties":{"id":16910,"name":"ПРАЖСКАЯ УЛИЦА / УЛИЦА БЕЛЫ КУНА","transportType":{"name":"Троллейбус","systemName":"trolley","monitorable":true,"id":1}},"id":16910,"geometry":{"type":"Point","coordinates":[3382744.8488516305,8371803.853997746]}},{"type":"Feature","properties":{"id":15446,"name":"СТАНЦИЯ МЕТРО \"МЕЖДУНАРОДНАЯ\"","transportType":{"name":"Троллейбус","systemName":"trolley","monitorable":true,"id":1}},"id":15446,"geometry":{"type":"Point","coordinates":[3381708.019114381,8371006.759851914]}},{"type":"Feature","properties":{"id":15450,"name":"УЛИЦА ТУРКУ","transportType":{"name":"Троллейбус","systemName":"trolley","monitorable":true,"id":1}},"id":15450,"geometry":{"type":"Point","coordinates":[3380884.254882511,8370230.5962633835]}},{"type":"Feature","properties":{"id":15451,"name":"БУДАПЕШТСКАЯ УЛИЦА, 19","transportType":{"name":"Троллейбус","systemName":"trolley","monitorable":true,"id":1}},"id":15451,"geometry":{"type":"Point","coordinates":[3381162.553609495,8369521.032461135]}},{"type":"Feature","properties":{"id":15677,"name":"БУДАПЕШТСКАЯ УЛИЦА, 33","transportType":{"name":"Троллейбус","systemName":"trolley","monitorable":true,"id":1}},"id":15677,"geometry":{"type":"Point","coordinates":[3381563.303776351,8368456.814744851]}},{"type":"Feature","properties":{"id":15329,"name":"БУДАПЕШТСКАЯ УЛИЦА / ПРОСПЕКТ СЛАВЫ","transportType":{"name":"Троллейбус","systemName":"trolley","monitorable":true,"id":1}},"id":15329,"geometry":{"type":"Point","coordinates":[3381684.642021315,8367771.805827678]}},{"type":"Feature","properties":{"id":15331,"name":"БЕЛГРАДСКАЯ УЛИЦА","transportType":{"name":"Троллейбус","systemName":"trolley","monitorable":true,"id":1}},"id":15331,"geometry":{"type":"Point","coordinates":[3380772.9353917185,8367503.583423271]}},{"type":"Feature","properties":{"id":15356,"name":"ПРОСПЕКТ КОСМОНАВТОВ / УЛИЦА ТИПАНОВА","transportType":{"name":"Троллейбус","systemName":"trolley","monitorable":true,"id":1}},"id":15356,"geometry":{"type":"Point","coordinates":[3378568.809474011,8367044.746223108]}},{"type":"Feature","properties":{"id":15360,"name":"УЛИЦА ТИПАНОВА, 21","transportType":{"name":"Троллейбус","systemName":"trolley","monitorable":true,"id":1}},"id":15360,"geometry":{"type":"Point","coordinates":[3377667.1215985855,8366993.766073894]}},{"type":"Feature","properties":{"id":15362,"name":"УЛИЦА ЛЕНСОВЕТА","transportType":{"name":"Троллейбус","systemName":"trolley","monitorable":true,"id":1}},"id":15362,"geometry":{"type":"Point","coordinates":[3376445.9467845843,8366978.2504462525]}},{"type":"Feature","properties":{"id":15366,"name":"МЕТРО \"МОСКОВСКАЯ\"","transportType":{"name":"Троллейбус","systemName":"trolley","monitorable":true,"id":1}},"id":15366,"geometry":{"type":"Point","coordinates":[3375479.6936044977,8367186.605884065]}},{"type":"Feature","properties":{"id":15368,"name":"ВАРШАВСКАЯ УЛИЦА","transportType":{"name":"Троллейбус","systemName":"trolley","monitorable":true,"id":1}},"id":15368,"geometry":{"type":"Point","coordinates":[3374472.252212819,8366905.105784095]}},{"type":"Feature","properties":{"id":16901,"name":"ПЛОЩАДЬ КОНСТИТУЦИИ","transportType":{"name":"Троллейбус","systemName":"trolley","monitorable":true,"id":1}},"id":16901,"geometry":{"type":"Point","coordinates":[3373837.7311152974,8366882.940878167]}},{"type":"Feature","properties":{"id":16888,"name":"ЛЕНИНСКИЙ ПРОСПЕКТ, 156","transportType":{"name":"Троллейбус","systemName":"trolley","monitorable":true,"id":1}},"id":16888,"geometry":{"type":"Point","coordinates":[3372788.210956098,8366874.96152834]}},{"type":"Feature","properties":{"id":16889,"name":"Ж/Д ПЛАТФОРМА ЛЕНИНСКИЙ ПРОСПЕКТ","transportType":{"name":"Троллейбус","systemName":"trolley","monitorable":true,"id":1}},"id":16889,"geometry":{"type":"Point","coordinates":[3371555.01363709,8366876.069770855]}},{"type":"Feature","properties":{"id":16892,"name":"ПРОСПЕКТ НАРОДНОГО ОПОЛЧЕНИЯ","transportType":{"name":"Троллейбус","systemName":"trolley","monitorable":true,"id":1}},"id":16892,"geometry":{"type":"Point","coordinates":[3370681.823551308,8366856.564726905]}},{"type":"Feature","properties":{"id":16893,"name":"МЕТРО \"ЛЕНИНСКИЙ ПРОСПЕКТ\"","transportType":{"name":"Троллейбус","systemName":"trolley","monitorable":true,"id":1}},"id":16893,"geometry":{"type":"Point","coordinates":[3369131.143044558,8366860.776038847]}},{"type":"Feature","properties":{"id":15684,"name":"УЛИЦА ЗИНЫ ПОРТНОВОЙ","transportType":{"name":"Троллейбус","systemName":"trolley","monitorable":true,"id":1}},"id":15684,"geometry":{"type":"Point","coordinates":[3367995.6842384664,8366860.776038847]}},{"type":"Feature","properties":{"id":15690,"name":"СОЛОМАХИНСКИЙ ПРОЕЗД","transportType":{"name":"Троллейбус","systemName":"trolley","monitorable":true,"id":1}},"id":15690,"geometry":{"type":"Point","coordinates":[3367014.959524578,8366867.425483648]}},{"type":"Feature","properties":{"id":15692,"name":"КРОНШТАДТСКАЯ ПЛОЩАДЬ","transportType":{"name":"Троллейбус","systemName":"trolley","monitorable":true,"id":1}},"id":15692,"geometry":{"type":"Point","coordinates":[3366355.9481390812,8366869.641966578]}},{"type":"Feature","properties":{"id":15696,"name":"ПРОСПЕКТ СТАЧЕК","transportType":{"name":"Троллейбус","systemName":"trolley","monitorable":true,"id":1}},"id":15696,"geometry":{"type":"Point","coordinates":[3365488.7693058015,8366876.291419372]}},{"type":"Feature","properties":{"id":15702,"name":"МОРСКОЙ ТЕХНИЧЕСКИЙ УНИВЕРСИТЕТ","transportType":{"name":"Троллейбус","systemName":"trolley","monitorable":true,"id":1}},"id":15702,"geometry":{"type":"Point","coordinates":[3364803.041242515,8366876.291419372]}},{"type":"Feature","properties":{"id":15704,"name":"ЛЕНИНСКИЙ ПРОСПЕКТ, 104","transportType":{"name":"Троллейбус","systemName":"trolley","monitorable":true,"id":1}},"id":15704,"geometry":{"type":"Point","coordinates":[3364433.4605330816,8366878.507904973]}},{"type":"Feature","properties":{"id":15708,"name":"ПРОСПЕКТ МАРШАЛА ЖУКОВА","transportType":{"name":"Троллейбус","systemName":"trolley","monitorable":true,"id":1}},"id":15708,"geometry":{"type":"Point","coordinates":[3364014.899247699,8366956.085320515]}},{"type":"Feature","properties":{"id":15710,"name":"ЛЕНИНСКИЙ ПРОСПЕКТ, 95","transportType":{"name":"Троллейбус","systemName":"trolley","monitorable":true,"id":1}},"id":15710,"geometry":{"type":"Point","coordinates":[3363603.0171317635,8367148.924145513]}},{"type":"Feature","properties":{"id":15713,"name":"УЛИЦА КОТИНА","transportType":{"name":"Троллейбус","systemName":"trolley","monitorable":true,"id":1}},"id":15713,"geometry":{"type":"Point","coordinates":[3362795.7281845305,8367503.583423271]}},{"type":"Feature","properties":{"id":15716,"name":"УЛИЦА ДЕСАНТНИКОВ","transportType":{"name":"Троллейбус","systemName":"trolley","monitorable":true,"id":1}},"id":15716,"geometry":{"type":"Point","coordinates":[3362365.1443941426,8367716.387176052]}},{"type":"Feature","properties":{"id":15717,"name":"БРЕСТСКИЙ БУЛЬВАР","transportType":{"name":"Троллейбус","systemName":"trolley","monitorable":true,"id":1}},"id":15717,"geometry":{"type":"Point","coordinates":[3361768.4719234905,8367984.617319608]}},{"type":"Feature","properties":{"id":15720,"name":"ЛЕНИНСКИЙ ПРОСПЕКТ, 79","transportType":{"name":"Троллейбус","systemName":"trolley","monitorable":true,"id":1}},"id":15720,"geometry":{"type":"Point","coordinates":[3361231.911977867,8368228.471369976]}},{"type":"Feature","properties":{"id":15723,"name":"ПРОСПЕКТ КУЗНЕЦОВА","transportType":{"name":"Троллейбус","systemName":"trolley","monitorable":true,"id":1}},"id":15723,"geometry":{"type":"Point","coordinates":[3360539.5047451328,8368536.625747064]}},{"type":"Feature","properties":{"id":24973,"name":"ЛЕНИНСКИЙ ПРОСПЕКТ, 72","transportType":{"name":"Троллейбус","systemName":"trolley","monitorable":true,"id":1}},"id":24973,"geometry":{"type":"Point","coordinates":[3359889.3989189,8368831.490550484]}},{"type":"Feature","properties":{"id":24968,"name":"УЛИЦА ДОБЛЕСТИ / ЛЕНИНСКИЙ ПРОСПЕКТ","transportType":{"name":"Троллейбус","systemName":"trolley","monitorable":true,"id":1}},"id":24968,"geometry":{"type":"Point","coordinates":[3359506.459870571,8369008.858516586]}},{"type":"Feature","properties":{"id":24969,"name":"ЛЕНИНСКИЙ ПРОСПЕКТ, 55","transportType":{"name":"Троллейбус","systemName":"trolley","monitorable":true,"id":1}},"id":24969,"geometry":{"type":"Point","coordinates":[3358671.563689622,8369385.779608317]}},{"type":"Feature","properties":{"id":25554,"name":"ПРОСПЕКТ ГЕРОЕВ","transportType":{"name":"Троллейбус","systemName":"trolley","monitorable":true,"id":1}},"id":25554,"geometry":{"type":"Point","coordinates":[3358018.118278665,8369611.941510222]}},{"type":"Feature","properties":{"id":24970,"name":"ЛЕНИНСКИЙ ПРОСПЕКТ, 55","transportType":{"name":"Троллейбус","systemName":"trolley","monitorable":true,"id":1}},"id":24970,"geometry":{"type":"Point","coordinates":[3358783.9963753233,8369254.963635004]}},{"type":"Feature","properties":{"id":16989,"name":"УЛИЦА ДОБЛЕСТИ","transportType":{"name":"Троллейбус","systemName":"trolley","monitorable":true,"id":1}},"id":16989,"geometry":{"type":"Point","coordinates":[3359758.0419197637,8368811.536921226]}},{"type":"Feature","properties":{"id":15731,"name":"ПРОСПЕКТ КУЗНЕЦОВА","transportType":{"name":"Троллейбус","systemName":"trolley","monitorable":true,"id":1}},"id":15731,"geometry":{"type":"Point","coordinates":[3360685.333278072,8368396.957059966]}},{"type":"Feature","properties":{"id":15733,"name":"ЛЕНИНСКИЙ ПРОСПЕКТ, 79","transportType":{"name":"Троллейбус","systemName":"trolley","monitorable":true,"id":1}},"id":15733,"geometry":{"type":"Point","coordinates":[3361305.38284179,8368130.928782319]}},{"type":"Feature","properties":{"id":15736,"name":"УЛИЦА ДЕСАНТНИКОВ","transportType":{"name":"Троллейбус","systemName":"trolley","monitorable":true,"id":1}},"id":15736,"geometry":{"type":"Point","coordinates":[3362224.881835743,8367714.170438649]}},{"type":"Feature","properties":{"id":15737,"name":"УЛИЦА КОТИНА","transportType":{"name":"Троллейбус","systemName":"trolley","monitorable":true,"id":1}},"id":15737,"geometry":{"type":"Point","coordinates":[3362949.5717208073,8367383.884010464]}},{"type":"Feature","properties":{"id":15739,"name":"ЛЕНИНСКИЙ ПРОСПЕКТ, 95","transportType":{"name":"Троллейбус","systemName":"trolley","monitorable":true,"id":1}},"id":15739,"geometry":{"type":"Point","coordinates":[3363777.788732309,8367002.632161492]}},{"type":"Feature","properties":{"id":15741,"name":"ПРОСПЕКТ МАРШАЛА ЖУКОВА","transportType":{"name":"Троллейбус","systemName":"trolley","monitorable":true,"id":1}},"id":15741,"geometry":{"type":"Point","coordinates":[3364431.2341432655,8366816.44656001]}},{"type":"Feature","properties":{"id":15742,"name":"МОРСКОЙ ТЕХНИЧЕСКИЙ УНИВЕРСИТЕТ","transportType":{"name":"Троллейбус","systemName":"trolley","monitorable":true,"id":1}},"id":15742,"geometry":{"type":"Point","coordinates":[3364865.38015736,8366816.44656001]}},{"type":"Feature","properties":{"id":15743,"name":"ПРОСПЕКТ СТАЧЕК","transportType":{"name":"Троллейбус","systemName":"trolley","monitorable":true,"id":1}},"id":15743,"geometry":{"type":"Point","coordinates":[3365501.014449789,8366816.44656001]}},{"type":"Feature","properties":{"id":15744,"name":"КРОНШТАДТСКАЯ ПЛОЩАДЬ","transportType":{"name":"Троллейбус","systemName":"trolley","monitorable":true,"id":1}},"id":15744,"geometry":{"type":"Point","coordinates":[3366355.9481390812,8366814.230093066]}},{"type":"Feature","properties":{"id":15746,"name":"СОЛОМАХИНСКИЙ ПРОЕЗД","transportType":{"name":"Троллейбус","systemName":"trolley","monitorable":true,"id":1}},"id":15746,"geometry":{"type":"Point","coordinates":[3367193.070709847,8366809.797161173]}},{"type":"Feature","properties":{"id":15367,"name":"УЛИЦА ЗИНЫ ПОРТНОВОЙ / ЛЕНИНСКИЙ ПРОСПЕКТ","transportType":{"name":"Троллейбус","systemName":"trolley","monitorable":true,"id":1}},"id":15367,"geometry":{"type":"Point","coordinates":[3368234.909824181,8366804.034353685]}},{"type":"Feature","properties":{"id":15370,"name":"МЕТРО \"ЛЕНИНСКИЙ ПРОСПЕКТ\"","transportType":{"name":"Троллейбус","systemName":"trolley","monitorable":true,"id":1}},"id":15370,"geometry":{"type":"Point","coordinates":[3369639.8731174828,8366792.065460222]}},{"type":"Feature","properties":{"id":15373,"name":"ПРОСПЕКТ НАРОДНОГО ОПОЛЧЕНИЯ","transportType":{"name":"Троллейбус","systemName":"trolley","monitorable":true,"id":1}},"id":15373,"geometry":{"type":"Point","coordinates":[3370691.84230548,8366796.498381457]}},{"type":"Feature","properties":{"id":15377,"name":"Ж/Д ПЛАТФОРМА ЛЕНИНСКИЙ ПРОСПЕКТ","transportType":{"name":"Троллейбус","systemName":"trolley","monitorable":true,"id":1}},"id":15377,"geometry":{"type":"Point","coordinates":[3371806.595686283,8366801.15295163]}},{"type":"Feature","properties":{"id":15381,"name":"ЛЕНИНСКИЙ ПРОСПЕКТ, 147","transportType":{"name":"Троллейбус","systemName":"trolley","monitorable":true,"id":1}},"id":15381,"geometry":{"type":"Point","coordinates":[3372853.666816685,8366805.364231933]}},{"type":"Feature","properties":{"id":16902,"name":"ПЛОЩАДЬ КОНСТИТУЦИИ","transportType":{"name":"Троллейбус","systemName":"trolley","monitorable":true,"id":1}},"id":16902,"geometry":{"type":"Point","coordinates":[3373862.2214032714,8366809.797161173]}},{"type":"Feature","properties":{"id":15380,"name":"ВАРШАВСКАЯ УЛИЦА","transportType":{"name":"Троллейбус","systemName":"trolley","monitorable":true,"id":1}},"id":15380,"geometry":{"type":"Point","coordinates":[3374717.155092564,8366838.611266125]}},{"type":"Feature","properties":{"id":15385,"name":"МЕТРО \"МОСКОВСКАЯ\"","transportType":{"name":"Троллейбус","systemName":"trolley","monitorable":true,"id":1}},"id":15385,"geometry":{"type":"Point","coordinates":[3375577.6547563956,8366619.183609865]}},{"type":"Feature","properties":{"id":15387,"name":"УЛИЦА ЛЕНСОВЕТА","transportType":{"name":"Троллейбус","systemName":"trolley","monitorable":true,"id":1}},"id":15387,"geometry":{"type":"Point","coordinates":[3376520.5308434153,8366860.776038847]}},{"type":"Feature","properties":{"id":15390,"name":"УЛИЦА ТИПАНОВА, 21","transportType":{"name":"Троллейбус","systemName":"trolley","monitorable":true,"id":1}},"id":15390,"geometry":{"type":"Point","coordinates":[3377280.842965533,8366911.755268866]}},{"type":"Feature","properties":{"id":15334,"name":"ПРОСПЕКТ КОСМОНАВТОВ / УЛИЦА ТИПАНОВА","transportType":{"name":"Троллейбус","systemName":"trolley","monitorable":true,"id":1}},"id":15334,"geometry":{"type":"Point","coordinates":[3379006.2950728284,8367029.230488226]}},{"type":"Feature","properties":{"id":15339,"name":"БЕЛГРАДСКАЯ УЛИЦА","transportType":{"name":"Троллейбус","systemName":"trolley","monitorable":true,"id":1}},"id":15339,"geometry":{"type":"Point","coordinates":[3380925.443094105,8367470.333391518]}},{"type":"Feature","properties":{"id":15748,"name":"БУДАПЕШТСКАЯ УЛИЦА, 46 / ПРОСПЕКТ СЛАВЫ","transportType":{"name":"Троллейбус","systemName":"trolley","monitorable":true,"id":1}},"id":15748,"geometry":{"type":"Point","coordinates":[3381808.2066560956,8367924.763466863]}},{"type":"Feature","properties":{"id":15750,"name":"БУДАПЕШТСКАЯ УЛИЦА, 40","transportType":{"name":"Троллейбус","systemName":"trolley","monitorable":true,"id":1}},"id":15750,"geometry":{"type":"Point","coordinates":[3381507.6440309538,8368700.684408396]}},{"type":"Feature","properties":{"id":15752,"name":"БУДАПЕШТСКАЯ УЛИЦА, 19","transportType":{"name":"Троллейбус","systemName":"trolley","monitorable":true,"id":1}},"id":15752,"geometry":{"type":"Point","coordinates":[3381129.157762257,8369676.243709384]}},{"type":"Feature","properties":{"id":15754,"name":"УЛИЦА БЕЛЫ КУНА","transportType":{"name":"Троллейбус","systemName":"trolley","monitorable":true,"id":1}},"id":15754,"geometry":{"type":"Point","coordinates":[3380946.5937973554,8370365.86461096]}},{"type":"Feature","properties":{"id":15755,"name":"СТАНЦИЯ МЕТРО \"МЕЖДУНАРОДНАЯ\"","transportType":{"name":"Троллейбус","systemName":"trolley","monitorable":true,"id":1}},"id":15755,"geometry":{"type":"Point","coordinates":[3382075.3734339993,8371250.713852321]}},{"type":"Feature","properties":{"id":25008,"name":"ПРАЖСКАЯ УЛИЦА","transportType":{"name":"Троллейбус","systemName":"trolley","monitorable":true,"id":1}},"id":25008,"geometry":{"type":"Point","coordinates":[3382974.834919609,8371929.391980714]}},{"type":"Feature","properties":{"id":25006,"name":"СОФИЙСКАЯ УЛИЦА","transportType":{"name":"Троллейбус","systemName":"trolley","monitorable":true,"id":1}},"id":25006,"geometry":{"type":"Point","coordinates":[3383890.994328838,8372475.041261328]}},{"type":"Feature","properties":{"id":25007,"name":"СОФИЙСКАЯ УЛИЦА, 41","transportType":{"name":"Троллейбус","systemName":"trolley","monitorable":true,"id":1}},"id":25007,"geometry":{"type":"Point","coordinates":[3384619.023798626,8371488.022305227]}},{"type":"Feature","properties":{"id":25005,"name":"СОФИЙСКАЯ УЛИЦА, 55","transportType":{"name":"Троллейбус","systemName":"trolley","monitorable":true,"id":1}},"id":25005,"geometry":{"type":"Point","coordinates":[3385202.3379303827,8370714.025703701]}},{"type":"Feature","properties":{"id":15352,"name":"СОФИЙСКАЯ УЛИЦА / ПРОСПЕКТ СЛАВЫ","transportType":{"name":"Троллейбус","systemName":"trolley","monitorable":true,"id":1}},"id":15352,"geometry":{"type":"Point","coordinates":[3386173.1552095907,8370064.951354901]}},{"type":"Feature","properties":{"id":15357,"name":"Ж/Д ПЛАТФОРМА СОРТИРОВОЧНАЯ (высадка)","transportType":{"name":"Троллейбус","systemName":"trolley","monitorable":true,"id":1}},"id":15357,"geometry":{"type":"Point","coordinates":[3386760.810801488,8370157.419339023]}}]}