{"type":"FeatureCollection","features":[{"type":"Feature","properties":{"id":3917,"name":"А.С. \"УЛ. КОСТЮШКО\" (ВЫСАДКИ И ПОСАДКИ НЕТ)","transportType":{"name":"Автобус","systemName":"bus","monitorable":true,"id":0}},"id":3917,"geometry":{"type":"Point","coordinates":[3373983.5596482367,8364606.959635169]}},{"type":"Feature","properties":{"id":1322,"name":"5-Й ПРЕДПОРТОВЫЙ ПРОЕЗД,УГ. УЛ. КОСТЮШКО","transportType":{"name":"Автобус","systemName":"bus","monitorable":true,"id":0}},"id":1322,"geometry":{"type":"Point","coordinates":[3374080.9642026806,8364474.23420207]}},{"type":"Feature","properties":{"id":17309,"name":"ВАРШАВСКАЯ УЛ.,73","transportType":{"name":"Автобус","systemName":"bus","monitorable":true,"id":0}},"id":17309,"geometry":{"type":"Point","coordinates":[3374690.4384147734,8365052.3495761035]}},{"type":"Feature","properties":{"id":1610,"name":"КРАСНОПУТИЛОВСКАЯ УЛ.","transportType":{"name":"Автобус","systemName":"bus","monitorable":true,"id":0}},"id":1610,"geometry":{"type":"Point","coordinates":[3374655.9293726278,8366134.914358625]}},{"type":"Feature","properties":{"id":1644,"name":"ЛЕНИНСКИЙ ПР.,УГ. ВАРШАВСКОЙ УЛ.","transportType":{"name":"Автобус","systemName":"bus","monitorable":true,"id":0}},"id":1644,"geometry":{"type":"Point","coordinates":[3374690.4384147734,8366847.477167215]}},{"type":"Feature","properties":{"id":14692,"name":"СТ.МЕТРО \"МОСКОВСКАЯ\" ","transportType":{"name":"Автобус","systemName":"bus","monitorable":true,"id":0}},"id":14692,"geometry":{"type":"Point","coordinates":[3375349.3384807794,8366067.318662357]}},{"type":"Feature","properties":{"id":2979,"name":"ПЛОЩАДЬ ПОБЕДЫ","transportType":{"name":"Автобус","systemName":"bus","monitorable":true,"id":0}},"id":2979,"geometry":{"type":"Point","coordinates":[3375230.8945425753,8364817.907140584]}},{"type":"Feature","properties":{"id":1510,"name":"ДУНАЙСКИЙ ПР.","transportType":{"name":"Автобус","systemName":"bus","monitorable":true,"id":0}},"id":1510,"geometry":{"type":"Point","coordinates":[3375412.9019100224,8362962.352068578]}},{"type":"Feature","properties":{"id":2121,"name":"СУПЕРМАРКЕТ \"О' КЕЙ\"","transportType":{"name":"Автобус","systemName":"bus","monitorable":true,"id":0}},"id":2121,"geometry":{"type":"Point","coordinates":[3375457.095747867,8361395.408533394]}},{"type":"Feature","properties":{"id":2145,"name":"ТОРГОВЫЙ ЦЕНТР \"МЕТРО\"","transportType":{"name":"Автобус","systemName":"bus","monitorable":true,"id":0}},"id":2145,"geometry":{"type":"Point","coordinates":[3375471.6786011606,8360719.470621061]}},{"type":"Feature","properties":{"id":20642,"name":"Ж.-Д. СТ. \"АЭРОПОРТ\"","transportType":{"name":"Автобус","systemName":"bus","monitorable":true,"id":0}},"id":20642,"geometry":{"type":"Point","coordinates":[3375573.8698937087,8358268.939799553]}},{"type":"Feature","properties":{"id":2152,"name":"ТРЦ \"ПУЛКОВО-III\"","transportType":{"name":"Автобус","systemName":"bus","monitorable":true,"id":0}},"id":2152,"geometry":{"type":"Point","coordinates":[3375605.595948586,8356036.779956653]}},{"type":"Feature","properties":{"id":21518,"name":"ДОРОГА НА ПУШКИН","transportType":{"name":"Автобус","systemName":"bus","monitorable":true,"id":0}},"id":21518,"geometry":{"type":"Point","coordinates":[3375750.311286617,8350669.875784306]}},{"type":"Feature","properties":{"id":1953,"name":"ПУЛКОВО","transportType":{"name":"Автобус","systemName":"bus","monitorable":true,"id":0}},"id":1953,"geometry":{"type":"Point","coordinates":[3376567.5076685306,8348880.005716496]}},{"type":"Feature","properties":{"id":2447,"name":"ЦВЕТОЧНЫЙ ПИТОМНИК","transportType":{"name":"Автобус","systemName":"bus","monitorable":true,"id":0}},"id":2447,"geometry":{"type":"Point","coordinates":[3374848.1781332274,8344643.895910346]}},{"type":"Feature","properties":{"id":19318,"name":"24 КМ ПУЛКОВСКОГО ШОССЕ","transportType":{"name":"Автобус","systemName":"bus","monitorable":true,"id":0}},"id":19318,"geometry":{"type":"Point","coordinates":[3372697.9308490646,8340588.668203256]}},{"type":"Feature","properties":{"id":18656,"name":"11 КМ","transportType":{"name":"Автобус","systemName":"bus","monitorable":true,"id":0}},"id":18656,"geometry":{"type":"Point","coordinates":[3369146.95041225,8338139.511119621]}},{"type":"Feature","properties":{"id":18657,"name":"СОВХОЗ \"НАГОРНЫЙ\"","transportType":{"name":"Автобус","systemName":"bus","monitorable":true,"id":0}},"id":18657,"geometry":{"type":"Point","coordinates":[3367977.6504809572,8338641.156713634]}},{"type":"Feature","properties":{"id":18658,"name":"8 КМ","transportType":{"name":"Автобус","systemName":"bus","monitorable":true,"id":0}},"id":18658,"geometry":{"type":"Point","coordinates":[3361574.8873290014,8339035.299183388]}},{"type":"Feature","properties":{"id":18659,"name":"7 КМ","transportType":{"name":"Автобус","systemName":"bus","monitorable":true,"id":0}},"id":18659,"geometry":{"type":"Point","coordinates":[3359500.3372985777,8339184.570954902]}},{"type":"Feature","properties":{"id":18660,"name":"САДОВОДСТВО \"ЗДОРОВЬЕ\"","transportType":{"name":"Автобус","systemName":"bus","monitorable":true,"id":0}},"id":18660,"geometry":{"type":"Point","coordinates":[3358319.12618177,8339283.719109713]}},{"type":"Feature","properties":{"id":18661,"name":"5 КМ","transportType":{"name":"Автобус","systemName":"bus","monitorable":true,"id":0}},"id":18661,"geometry":{"type":"Point","coordinates":[3356457.1963787624,8339769.76306256]}},{"type":"Feature","properties":{"id":18662,"name":"4 КМ","transportType":{"name":"Автобус","systemName":"bus","monitorable":true,"id":0}},"id":18662,"geometry":{"type":"Point","coordinates":[3354302.607634458,8340336.008171366]}},{"type":"Feature","properties":{"id":18663,"name":"3 КМ","transportType":{"name":"Автобус","systemName":"bus","monitorable":true,"id":0}},"id":18663,"geometry":{"type":"Point","coordinates":[3352894.527395414,8340441.134896764]}},{"type":"Feature","properties":{"id":26109,"name":"ПЕТРОВСКАЯ МЕЛЬНИЦА","transportType":{"name":"Автобус","systemName":"bus","monitorable":true,"id":0}},"id":26109,"geometry":{"type":"Point","coordinates":[3352531.4032164463,8340389.675619405]}},{"type":"Feature","properties":{"id":19842,"name":"ПР. КРАСНЫХ КОМАНДИРОВ","transportType":{"name":"Автобус","systemName":"bus","monitorable":true,"id":0}},"id":19842,"geometry":{"type":"Point","coordinates":[3350041.0748879104,8339877.752636441]}},{"type":"Feature","properties":{"id":20843,"name":"УЛ. ПЕРВОГО МАЯ","transportType":{"name":"Автобус","systemName":"bus","monitorable":true,"id":0}},"id":20843,"geometry":{"type":"Point","coordinates":[3349416.795183541,8340608.987392559]}},{"type":"Feature","properties":{"id":3460,"name":"УЛ. МАССАЛЬСКОГО","transportType":{"name":"Автобус","systemName":"bus","monitorable":true,"id":0}},"id":3460,"geometry":{"type":"Point","coordinates":[3349737.729275498,8341968.954140926]}},{"type":"Feature","properties":{"id":20555,"name":"УЛ. ОСВОБОЖДЕНИЯ","transportType":{"name":"Автобус","systemName":"bus","monitorable":true,"id":0}},"id":20555,"geometry":{"type":"Point","coordinates":[3349601.6968577495,8342310.697033678]}},{"type":"Feature","properties":{"id":20556,"name":"УЛ. СПИРИНА","transportType":{"name":"Автобус","systemName":"bus","monitorable":true,"id":0}},"id":20556,"geometry":{"type":"Point","coordinates":[3349063.3558002724,8342614.899067425]}},{"type":"Feature","properties":{"id":20557,"name":"БРОНЕТАНКОВАЯ УЛ.","transportType":{"name":"Автобус","systemName":"bus","monitorable":true,"id":0}},"id":20557,"geometry":{"type":"Point","coordinates":[3349155.8622971214,8342985.172047859]}},{"type":"Feature","properties":{"id":24401,"name":"ГЕОЛОГИЧЕСКАЯ УЛ.","transportType":{"name":"Автобус","systemName":"bus","monitorable":true,"id":0}},"id":24401,"geometry":{"type":"Point","coordinates":[3348754.666852303,8343774.604778057]}},{"type":"Feature","properties":{"id":19890,"name":"ГЕОЛОГИЧЕСКАЯ УЛ., 75","transportType":{"name":"Автобус","systemName":"bus","monitorable":true,"id":0}},"id":19890,"geometry":{"type":"Point","coordinates":[3348044.559820533,8344520.589108948]}},{"type":"Feature","properties":{"id":25787,"name":"ГЕОЛОГИЧЕСКАЯ УЛ., УГ. УЛ. СПИРИНА","transportType":{"name":"Автобус","systemName":"bus","monitorable":true,"id":0}},"id":25787,"geometry":{"type":"Point","coordinates":[3348906.506637745,8343706.550717409]}},{"type":"Feature","properties":{"id":22230,"name":"УЛ. СПИРИНА, УГ. УЛ. ОСВОБОЖДЕНИЯ","transportType":{"name":"Автобус","systemName":"bus","monitorable":true,"id":0}},"id":22230,"geometry":{"type":"Point","coordinates":[3349043.540930911,8342543.983747623]}},{"type":"Feature","properties":{"id":2276,"name":"УЛ. МАССАЛЬСКОГО","transportType":{"name":"Автобус","systemName":"bus","monitorable":true,"id":0}},"id":2276,"geometry":{"type":"Point","coordinates":[3349605.259081454,8341763.518384515]}},{"type":"Feature","properties":{"id":21255,"name":"ПР. ЛЕНИНА, УГ. УЛ. ПЕРВОГО МАЯ","transportType":{"name":"Автобус","systemName":"bus","monitorable":true,"id":0}},"id":21255,"geometry":{"type":"Point","coordinates":[3349444.291097767,8340502.7539881915]}},{"type":"Feature","properties":{"id":19859,"name":"ПР. КРАСНЫХ КОМАНДИРОВ","transportType":{"name":"Автобус","systemName":"bus","monitorable":true,"id":0}},"id":19859,"geometry":{"type":"Point","coordinates":[3350232.321773093,8339745.912817412]}},{"type":"Feature","properties":{"id":26108,"name":"ПЕТРОВСКАЯ МЕЛЬНИЦА","transportType":{"name":"Автобус","systemName":"bus","monitorable":true,"id":0}},"id":26108,"geometry":{"type":"Point","coordinates":[3352651.9622249757,8340384.816822042]}},{"type":"Feature","properties":{"id":18666,"name":"3 КМ","transportType":{"name":"Автобус","systemName":"bus","monitorable":true,"id":0}},"id":18666,"geometry":{"type":"Point","coordinates":[3352900.538647917,8340368.252764157]}},{"type":"Feature","properties":{"id":18668,"name":"4 КМ","transportType":{"name":"Автобус","systemName":"bus","monitorable":true,"id":0}},"id":18668,"geometry":{"type":"Point","coordinates":[3354626.3247136855,8340233.312290106]}},{"type":"Feature","properties":{"id":18670,"name":"5 КМ","transportType":{"name":"Автобус","systemName":"bus","monitorable":true,"id":0}},"id":18670,"geometry":{"type":"Point","coordinates":[3357136.8018700555,8339374.477273545]}},{"type":"Feature","properties":{"id":18671,"name":"САДОВОДСТВО \"ЗДОРОВЬЕ\"","transportType":{"name":"Автобус","systemName":"bus","monitorable":true,"id":0}},"id":18671,"geometry":{"type":"Point","coordinates":[3358572.3780233245,8339205.990376743]}},{"type":"Feature","properties":{"id":18673,"name":"7 КМ","transportType":{"name":"Автобус","systemName":"bus","monitorable":true,"id":0}},"id":18673,"geometry":{"type":"Point","coordinates":[3359543.306622024,8339130.912263653]}},{"type":"Feature","properties":{"id":18675,"name":"8 КМ","transportType":{"name":"Автобус","systemName":"bus","monitorable":true,"id":0}},"id":18675,"geometry":{"type":"Point","coordinates":[3362200.725506241,8339010.126430465]}},{"type":"Feature","properties":{"id":18676,"name":"СОВХОЗ \"НАГОРНЫЙ\"","transportType":{"name":"Автобус","systemName":"bus","monitorable":true,"id":0}},"id":18676,"geometry":{"type":"Point","coordinates":[3368142.5146468226,8338487.03837607]}},{"type":"Feature","properties":{"id":18677,"name":"11 КМ","transportType":{"name":"Автобус","systemName":"bus","monitorable":true,"id":0}},"id":18677,"geometry":{"type":"Point","coordinates":[3369424.0246248343,8337936.61045397]}},{"type":"Feature","properties":{"id":19337,"name":"24 КМ ПУЛКОВСКОГО ШОССЕ","transportType":{"name":"Автобус","systemName":"bus","monitorable":true,"id":0}},"id":19337,"geometry":{"type":"Point","coordinates":[3373011.963132593,8340923.279364834]}},{"type":"Feature","properties":{"id":3625,"name":"ЦВЕТОЧНЫЙ ПИТОМНИК","transportType":{"name":"Автобус","systemName":"bus","monitorable":true,"id":0}},"id":3625,"geometry":{"type":"Point","coordinates":[3374996.6783339465,8344772.066452949]}},{"type":"Feature","properties":{"id":3148,"name":"ПУЛКОВО","transportType":{"name":"Автобус","systemName":"bus","monitorable":true,"id":0}},"id":3148,"geometry":{"type":"Point","coordinates":[3376632.7408901346,8348892.830027003]}},{"type":"Feature","properties":{"id":21519,"name":"ДОРОГА НА ПУШКИН","transportType":{"name":"Автобус","systemName":"bus","monitorable":true,"id":0}},"id":21519,"geometry":{"type":"Point","coordinates":[3375873.6532824156,8350797.266327975]}},{"type":"Feature","properties":{"id":3338,"name":"ТРЦ \"ПУЛКОВО-III\"","transportType":{"name":"Автобус","systemName":"bus","monitorable":true,"id":0}},"id":3338,"geometry":{"type":"Point","coordinates":[3375707.119324189,8356295.953873324]}},{"type":"Feature","properties":{"id":2727,"name":"Ж.Д.  ПЛАТФОРМА \"АЭРОПОРТ\"","transportType":{"name":"Автобус","systemName":"bus","monitorable":true,"id":0}},"id":2727,"geometry":{"type":"Point","coordinates":[3375647.786035596,8358478.59917691]}},{"type":"Feature","properties":{"id":3331,"name":"ТОРГОВЫЙ ЦЕНТР \"МЕТРО\"","transportType":{"name":"Автобус","systemName":"bus","monitorable":true,"id":0}},"id":3331,"geometry":{"type":"Point","coordinates":[3375579.1019097767,8360608.961105361]}},{"type":"Feature","properties":{"id":3310,"name":"СУПЕРМАРКЕТ \"О' КЕЙ\"","transportType":{"name":"Автобус","systemName":"bus","monitorable":true,"id":0}},"id":3310,"geometry":{"type":"Point","coordinates":[3375553.721065876,8361498.177780973]}},{"type":"Feature","properties":{"id":2719,"name":"ДУНАЙСКИЙ ПР.","transportType":{"name":"Автобус","systemName":"bus","monitorable":true,"id":0}},"id":2719,"geometry":{"type":"Point","coordinates":[3375517.5422313674,8363089.290396275]}},{"type":"Feature","properties":{"id":19315,"name":"ПЛ. ПОБЕДЫ","transportType":{"name":"Автобус","systemName":"bus","monitorable":true,"id":0}},"id":19315,"geometry":{"type":"Point","coordinates":[3375573.8698937087,8365047.474515759]}},{"type":"Feature","properties":{"id":2081,"name":"СТ. МЕТРО \"МОСКОВСКАЯ\"","transportType":{"name":"Автобус","systemName":"bus","monitorable":true,"id":0}},"id":2081,"geometry":{"type":"Point","coordinates":[3375415.016980347,8366377.155826695]}},{"type":"Feature","properties":{"id":3268,"name":"СТ. МЕТРО \"МОСКОВСКАЯ\"","transportType":{"name":"Автобус","systemName":"bus","monitorable":true,"id":0}},"id":3268,"geometry":{"type":"Point","coordinates":[3375619.9561628974,8367186.605884065]}},{"type":"Feature","properties":{"id":2851,"name":"ЛЕНИНСКИЙ ПР.,УГ. ВАРШАВСКОЙ УЛ.","transportType":{"name":"Автобус","systemName":"bus","monitorable":true,"id":0}},"id":2851,"geometry":{"type":"Point","coordinates":[3374604.054489918,8366761.92166644]}},{"type":"Feature","properties":{"id":2817,"name":"КРАСНОПУТИЛОВСКАЯ УЛ.","transportType":{"name":"Автобус","systemName":"bus","monitorable":true,"id":0}},"id":2817,"geometry":{"type":"Point","coordinates":[3374631.884362617,8366064.437548082]}},{"type":"Feature","properties":{"id":17310,"name":"ВАРШАВСКАЯ УЛ.,73","transportType":{"name":"Автобус","systemName":"bus","monitorable":true,"id":0}},"id":17310,"geometry":{"type":"Point","coordinates":[3374527.577999743,8365096.4468592005]}},{"type":"Feature","properties":{"id":22839,"name":"УЛ. КОСТЮШКО","transportType":{"name":"Автобус","systemName":"bus","monitorable":true,"id":0}},"id":22839,"geometry":{"type":"Point","coordinates":[3374243.490659239,8364513.674899415]}}]}